{
	"id": 123,
	"start_date": 1434365326935,
	"end_date": 1434369346935,
	"status": 0,
	"actions": {
		"total": 123,
		"remediated": 3,
		"pendingTime": 1200
	},
	"detection": {
		"detection_system_id": 1,
		"timestamp": 1434365326935,
		"alert": {
			"alertId": 345793,
			"entity": {
				"type": 1,
				"name": "c:\\1.txt"
			},
			"host": {
				"id": 435,
				"name": "BARAK-PC"
			}
		}
	},
	"external_sources": {
		"data": [
			{
				"id": 1,
				"data": "2 rules added to block ip 192.15.3.5 to 123.52.6.7 on any port"
			}
		],
		"remediation": [
			{
				"id": 5,
				"data": "I fixed it mommy!"
			}
		]
	},
	"entities": [
		{
			"id": 1,
			"results": [
				{ "count": 25, "result": "remediated" },
				{ "count": 30, "result": "failed" },
				{ "count": 45, "result": "benign" }
			]
		}
	],
	"hosts": {
		"total": 120,
		"groups": 4,
		"results": {
			"remediated": 3,
			"failed": 6,
			"benign": 10
		}
	}
}
